{"geometry": {"width": 108800, "height": 96000}, "towns": [{"pos": {"y": 49655.0, "x": 4459.0}, "code_name": "Belaja", "label": {"ru": "\u0411\u0435\u043b\u0430\u044f", "en": "Belaja"}}, {"pos": {"y": 43090.0, "x": 49485.0}, "code_name": "Belenhino", "label": {"ru": "\u0411\u0435\u043b\u0435\u043d\u0445\u0438\u043d\u043e", "en": "Belenhino"}}, {"pos": {"y": 36983.0, "x": 81111.0}, "code_name": "Beliy_Kolodec", "label": {"ru": "\u0411\u0435\u043b\u044b\u0439 \u041a\u043e\u043b\u043e\u0434\u0435\u0446", "en": "Beliy Colodec"}}, {"pos": {"y": 69252.0, "x": 31797.0}, "code_name": "Bikanovo", "label": {"ru": "\u0411\u044b\u043a\u0430\u043d\u043e\u0432\u043e", "en": "Bikanovo"}}, {"pos": {"y": 65260.0, "x": 43865.0}, "code_name": "Bobrishovo", "label": {"ru": "\u0411\u043e\u0431\u0440\u044b\u0448\u043e\u0432\u043e", "en": "Bobrishovo"}}, {"pos": {"y": 55102.0, "x": 91749.0}, "code_name": "Bogoslovka", "label": {"ru": "\u0411\u043e\u0433\u043e\u0441\u043b\u043e\u0432\u043a\u0430", "en": "Bogoslovka"}}, {"pos": {"y": 39247.0, "x": 96378.0}, "code_name": "Bolshaya_Khalan", "label": {"ru": "\u0411\u043e\u043b\u044c\u0448\u0430\u044f \u0425\u0430\u043b\u0430\u043d\u044c", "en": "Bolshaya Khalan"}}, {"pos": {"y": 61230.0, "x": 64830.0}, "code_name": "Bolshie_Seti", "label": {"ru": "\u0411\u043e\u043b\u044c\u0448\u0438\u0435 \u0421\u0435\u0442\u0438", "en": "Bolshiye Seti"}}, {"pos": {"y": 10688.0, "x": 74338.0}, "code_name": "Bolshoye_Gorodische", "label": {"ru": "\u0411\u043e\u043b\u044c\u0448\u043e\u0435 \u0413\u043e\u0440\u043e\u0434\u0438\u0449\u0435", "en": "Bolshie Gorodishe"}}, {"pos": {"y": 6375.0, "x": 12196.0}, "code_name": "Borisovka", "label": {"ru": "\u0411\u043e\u0440\u0438\u0441\u043e\u0432\u043a\u0430", "en": "Borisovka"}}, {"pos": {"y": 65603.0, "x": 74641.0}, "code_name": "Chuevo", "label": {"ru": "\u0427\u0443\u0435\u0432\u043e", "en": "Chuevo"}}, {"pos": {"y": 59762.0, "x": 18031.0}, "code_name": "Dolgie_Budy", "label": {"ru": "\u0414\u043e\u043b\u0433\u0438\u0435 \u0411\u0443\u0434\u044b", "en": "Dolgie Budy"}}, {"pos": {"y": 22182.0, "x": 54809.0}, "code_name": "Gostischevo", "label": {"ru": "\u0413\u043e\u0441\u0442\u0438\u0449\u0435\u0432\u043e", "en": "Gostishevo"}}, {"pos": {"y": 69617.0, "x": 95714.0}, "code_name": "Gubkin", "label": {"ru": "\u0413\u0443\u0431\u043a\u0438\u043d", "en": "Gubkin"}}, {"pos": {"y": 47577.0, "x": 68185.0}, "code_name": "Holodnoe", "label": {"ru": "\u0425\u043e\u043b\u043e\u0434\u043d\u043e\u0435", "en": "Holodnoe"}}, {"pos": {"y": 15573.0, "x": 80670.0}, "code_name": "Ivica", "label": {"ru": "\u0418\u0432\u0438\u0446\u0430", "en": "Ivica"}}, {"pos": {"y": 30796.0, "x": 94623.0}, "code_name": "Jablonevo", "label": {"ru": "\u042f\u0431\u043b\u043e\u043d\u0435\u0432\u043e", "en": "Jablonevo"}}, {"pos": {"y": 60090.0, "x": 28487.0}, "code_name": "Kamenka", "label": {"ru": "\u041a\u0430\u043c\u0435\u043d\u043a\u0430", "en": "Kamenka"}}, {"pos": {"y": 24026.0, "x": 84487.0}, "code_name": "Korocha", "label": {"ru": "\u041a\u043e\u0440\u043e\u0447\u0430", "en": "Korocha"}}, {"pos": {"y": 44385.0, "x": 85019.0}, "code_name": "Korochka", "label": {"ru": "\u041a\u043e\u0440\u043e\u0447\u043a\u0430", "en": "Korochka"}}, {"pos": {"y": 76013.0, "x": 38411.0}, "code_name": "Kotelnikovo", "label": {"ru": "\u041a\u043e\u0442\u0435\u043b\u044c\u043d\u0438\u043a\u043e\u0432\u043e", "en": "Kotelnikovo"}}, {"pos": {"y": 72276.0, "x": 43423.0}, "code_name": "Kotovo", "label": {"ru": "\u041a\u043e\u0442\u043e\u0432\u043e", "en": "Kotovo"}}, {"pos": {"y": 33624.0, "x": 101414.0}, "code_name": "Loznoe", "label": {"ru": "\u041b\u043e\u0437\u043d\u043e\u0435", "en": "Loznoe"}}, {"pos": {"y": 80244.0, "x": 79440.0}, "code_name": "Manturovo", "label": {"ru": "\u041c\u0430\u043d\u0442\u0443\u0440\u043e\u0432\u043e", "en": "Manturovo"}}, {"pos": {"y": 84831.0, "x": 19051.0}, "code_name": "Medvedka", "label": {"ru": "\u0420\u0435\u0443\u0442\u0435\u0446", "en": "Medvedka"}}, {"pos": {"y": 79897.0, "x": 11716.0}, "code_name": "Medvedka2", "label": {"ru": "\u0420\u0435\u0443\u0442\u0435\u0446", "en": "Medvedka"}}, {"pos": {"y": 57849.0, "x": 77771.0}, "code_name": "Morozovo", "label": {"ru": "\u041c\u043e\u0440\u043e\u0437\u043e\u0432\u043e", "en": "Morozovo"}}, {"pos": {"y": 42245.0, "x": 28316.0}, "code_name": "Nizjnie_Peny", "label": {"ru": "\u041d\u0438\u0436\u043d\u0438\u0435 \u041f\u0435\u043d\u044b", "en": "Nizhniye Peny"}}, {"pos": {"y": 76910.0, "x": 68186.0}, "code_name": "Orljanka", "label": {"ru": "\u041e\u0440\u043b\u044f\u043d\u043a\u0430", "en": "Orljanka"}}, {"pos": {"y": 49816.0, "x": 19160.0}, "code_name": "Peny", "label": {"ru": "\u041f\u0435\u043d\u044b", "en": "Peny"}}, {"pos": {"y": 43141.0, "x": 64732.0}, "code_name": "Podolhi", "label": {"ru": "\u041f\u043e\u0434\u043e\u043b\u044c\u0445\u0438", "en": "Podolhi"}}, {"pos": {"y": 36339.0, "x": 37041.0}, "code_name": "Pokrovka", "label": {"ru": "\u041f\u043e\u043a\u0440\u043e\u0432\u043a\u0430", "en": "Pokrovka"}}, {"pos": {"y": 69581.0, "x": 57799.0}, "code_name": "Prilepi", "label": {"ru": "\u041f\u0440\u0438\u043b\u0435\u043f\u044b", "en": "Prilepi"}}, {"pos": {"y": 67795.0, "x": 54076.0}, "code_name": "Pristen", "label": {"ru": "\u041f\u0440\u0438\u0441\u0442\u0435\u043d\u044c", "en": "Pristen"}}, {"pos": {"y": 49106.0, "x": 62597.0}, "code_name": "Priznachnoe", "label": {"ru": "\u041f\u0440\u0438\u0437\u043d\u0430\u0447\u043d\u043e\u0435", "en": "Prizrachnoe"}}, {"pos": {"y": 17343.0, "x": 12975.0}, "code_name": "Proletarskiy", "label": {"ru": "\u041f\u0440\u043e\u043b\u0435\u0442\u0430\u0440\u0441\u043a\u0438\u0439", "en": "Proletarskiy"}}, {"pos": {"y": 11381.0, "x": 38210.0}, "code_name": "Pushkarnoye", "label": {"ru": "\u041f\u0443\u0448\u043a\u0430\u0440\u043d\u043e\u0435", "en": "Pushkarnoye"}}, {"pos": {"y": 29604.0, "x": 4581.0}, "code_name": "Rakitnoye", "label": {"ru": "\u0420\u0430\u043a\u0438\u0442\u043d\u043e\u0435", "en": "Rakitnoe"}}, {"pos": {"y": 35829.0, "x": 23144.0}, "code_name": "Rakovo", "label": {"ru": "\u0420\u0430\u043a\u043e\u0432\u043e", "en": "Rakovo"}}, {"pos": {"y": 61594.0, "x": 24991.0}, "code_name": "Ribinskie_Budi", "label": {"ru": "\u0420\u044b\u0431\u0438\u043d\u0441\u043a\u0438\u0435 \u0411\u0443\u0434\u044b", "en": "Ribinskiye Budi"}}, {"pos": {"y": 28943.0, "x": 60033.0}, "code_name": "Rzhavets", "label": {"ru": "\u0420\u0436\u0430\u0432\u0435\u0446", "en": "Rzhavets"}}, {"pos": {"y": 73188.0, "x": 60195.0}, "code_name": "Saraevka", "label": {"ru": "\u0421\u0430\u0440\u0430\u0435\u0432\u043a\u0430", "en": "Saraevka"}}, {"pos": {"y": 76136.0, "x": 61506.0}, "code_name": "Sazanovka", "label": {"ru": "\u0421\u0430\u0437\u0430\u043d\u043e\u0432\u043a\u0430", "en": "Sazanovka"}}, {"pos": {"y": 62410.0, "x": 93658.0}, "code_name": "Sergievka", "label": {"ru": "\u0421\u0435\u0440\u0433\u0438\u0435\u0432\u043a\u0430", "en": "Sergievka"}}, {"pos": {"y": 32340.0, "x": 54448.0}, "code_name": "Shakhovo", "label": {"ru": "\u0428\u0430\u0445\u043e\u0432\u043e", "en": "Shakhovo"}}, {"pos": {"y": 64162.0, "x": 27460.0}, "code_name": "Shevelovo", "label": {"ru": "\u0428\u0435\u0432\u0435\u043b\u043e\u0432\u043e", "en": "Shevelovo"}}, {"pos": {"y": 16335.0, "x": 52533.0}, "code_name": "Shljahovo", "label": {"ru": "\u0428\u043b\u044f\u0445\u043e\u0432\u043e", "en": "Shljahovo"}}, {"pos": {"y": 15200.0, "x": 98570.0}, "code_name": "Sidorovka", "label": {"ru": "\u0421\u0438\u0434\u043e\u0440\u043e\u0432\u043a\u0430", "en": "Sidorovka"}}, {"pos": {"y": 51798.0, "x": 85393.0}, "code_name": "Skorodnoye", "label": {"ru": "\u0421\u043a\u043e\u0440\u043e\u0434\u043d\u043e\u0435", "en": "Skorodnoye"}}, {"pos": {"y": 83358.0, "x": 55997.0}, "code_name": "Solintsevo", "label": {"ru": "\u0421\u043e\u043b\u043d\u0446\u0435\u0432\u043e", "en": "Solintsevo"}}, {"pos": {"y": 21041.0, "x": 46770.0}, "code_name": "Streletskoe", "label": {"ru": "\u0421\u0442\u0440\u0435\u043b\u0435\u0446\u043a\u043e\u0435", "en": "Streletskoe"}}, {"pos": {"y": 85987.0, "x": 63294.0}, "code_name": "Subbotino", "label": {"ru": "\u0421\u0443\u0431\u0431\u043e\u0442\u0438\u043d\u043e", "en": "Subbotino"}}, {"pos": {"y": 86483.0, "x": 73357.0}, "code_name": "Svinec", "label": {"ru": "\u0421\u0432\u0438\u043d\u0435\u0446", "en": "Svinec"}}, {"pos": {"y": 13949.0, "x": 25412.0}, "code_name": "Tomarovka", "label": {"ru": "\u0422\u043e\u043c\u0430\u0440\u043e\u0432\u043a\u0430", "en": "Tomarovka"}}, {"pos": {"y": 59767.0, "x": 72341.0}, "code_name": "Ukolovo", "label": {"ru": "\u0423\u043a\u043e\u043b\u043e\u0432\u043e", "en": "Ukolovo"}}, {"pos": {"y": 28795.0, "x": 103001.0}, "code_name": "Vasildol", "label": {"ru": "\u0412\u0430\u0441\u0438\u043b\u044c\u0434\u043e\u043b", "en": "Vasildol"}}, {"pos": {"y": 23081.0, "x": 105160.0}, "code_name": "Velocomikhaylovka", "label": {"ru": "\u0412\u0435\u043b\u0438\u043a\u043e\u043c\u0438\u0445\u0430\u0439\u043b\u043e\u0432\u043a\u0430", "en": "Velikomikhaylovka"}}, {"pos": {"y": 58187.0, "x": 49465.0}, "code_name": "Verh_Olshanka", "label": {"ru": "\u0412\u0435\u0440\u0445\u043d\u044f\u044f \u041e\u043b\u044c\u0448\u0430\u043d\u043a\u0430", "en": "Verhniaja Olshanka"}}, {"pos": {"y": 56767.0, "x": 65193.0}, "code_name": "Vjazovoe", "label": {"ru": "\u0412\u044f\u0437\u043e\u0432\u043e\u0435", "en": "Vjazovoe"}}, {"pos": {"y": 32306.0, "x": 37662.0}, "code_name": "Yakovlevo", "label": {"ru": "\u042f\u043a\u043e\u0432\u043b\u0435\u0432\u043e", "en": "Yakovlevo"}}, {"pos": {"y": 84081.0, "x": 40554.0}, "code_name": "Znamenka", "label": {"ru": "\u0417\u043d\u0430\u043c\u0435\u043d\u043a\u0430", "en": "Znamenka"}}, {"pos": {"y": 63534.0, "x": 38078.0}, "code_name": "Oboyan", "label": {"ru": "\u041e\u0431\u043e\u044f\u043d\u044c", "en": "Oboyan"}}, {"pos": {"y": 47279.0, "x": 55417.0}, "code_name": "Prokhorovka", "label": {"ru": "\u041f\u0440\u043e\u0445\u043e\u0440\u043e\u0432\u043a\u0430", "en": "Prokhorovka"}}, {"pos": {"y": 74696.0, "x": 100831.0}, "code_name": "Stariy_Oskol", "label": {"ru": "\u0421\u0442\u0430\u0440\u044b\u0439 \u041e\u0441\u043a\u043e\u043b", "en": "Stariy Oskol"}}, {"pos": {"y": 5787.0, "x": 47656.0}, "code_name": "Belgorod", "label": {"ru": "\u0411\u0435\u043b\u0433\u043e\u0440\u043e\u0434", "en": "Belgorod"}}], "airfields": [{"pos": {"y": 60413.0, "x": 36367.0}, "type": 1, "id": 1, "landing_vector": 300}, {"pos": {"y": 79960.0, "x": 53994.0}, "type": 1, "id": 2, "landing_vector": 245}, {"pos": {"y": 38375.0, "x": 71116.0}, "type": 1, "id": 3, "landing_vector": 80}, {"pos": {"y": 38015.0, "x": 85747.0}, "type": 1, "id": 4, "landing_vector": 220}, {"pos": {"y": 65232.0, "x": 98368.0}, "type": 1, "id": 5, "landing_vector": 120}, {"pos": {"y": 8908.0, "x": 88546.0}, "type": 1, "id": 6, "landing_vector": 105}, {"pos": {"y": 4966.52, "x": 52646.35}, "type": 1, "id": 7, "landing_vector": 125}, {"pos": {"y": 17408.0, "x": 41007.0}, "type": 1, "id": 8, "landing_vector": 115}, {"pos": {"y": 11393.0, "x": 13158.0}, "type": 1, "id": 9, "landing_vector": 45}], "code_name": "Prokhorovka"}